jqdatasdk/__init__.py
jqdatasdk/alpha101.py
jqdatasdk/alpha191.py
jqdatasdk/api.py
jqdatasdk/calendar_service.py
jqdatasdk/client.py
jqdatasdk/exceptions.py
jqdatasdk/finance_service.py
jqdatasdk/finance_tables.py
jqdatasdk/fundamentals_tables_gen.py
jqdatasdk/table.py
jqdatasdk/technical_analysis.py
jqdatasdk/thriftclient.py
jqdatasdk/utils.py
jqdatasdk/version.py
jqdatasdk/compat/__init__.py
jqdatasdk/compat/pickle_compat.py
jqdatasdk-1.9.7.dist-info/LICENSE
jqdatasdk-1.9.7.dist-info/METADATA
jqdatasdk-1.9.7.dist-info/WHEEL
jqdatasdk-1.9.7.dist-info/top_level.txt
jqdatasdk-1.9.7.dist-info/RECORD
