Metadata-Version: 2.1
Name: jqdatasdk
Version: 1.9.7
Summary: jqdatasdk<easy utility for getting financial market data of China>
Home-page: https://www.joinquant.com/data
Author: JoinQuant
Author-email: xlx@joinquant.com
Maintainer: tech_data
Maintainer-email: tech_data@joinquant.com
License: Apache License v2
Platform: all
Classifier: Programming Language :: Python
Classifier: Operating System :: Microsoft :: Windows
Classifier: Operating System :: Unix
Classifier: Programming Language :: Python :: 2.7
Classifier: Programming Language :: Python :: 3.4
Classifier: Programming Language :: Python :: 3.5
Classifier: Programming Language :: Python :: 3.6
License-File: LICENSE
